pypibrunohw/__init__.py
pypibrunohw-1.0.0.dist-info/WHEEL
pypibrunohw-1.0.0.dist-info/entry_points.txt
pypibrunohw-1.0.0.dist-info/METADATA
pypibrunohw-1.0.0.dist-info/RECORD
