Metadata-Version: 2.3
Name: pypibrunohw
Version: 1.0.0
Summary: A sample Python package for demonstration purposes
Author: Bruno Carnazzi
Author-email: Bruno Carnazzi <bcarnazzi@gmail.com>
Requires-Dist: click>=8.2.1
Requires-Python: >=3.13
